watson/__init__.py
watson/form/__init__.py
watson/form/decorators.py
watson/form/fields.py
watson/form/types.py
watson/form/validators.py
watson_form-4.4.2.dist-info/AUTHORS
watson_form-4.4.2.dist-info/LICENSE
watson_form-4.4.2.dist-info/METADATA
watson_form-4.4.2.dist-info/WHEEL
watson_form-4.4.2.dist-info/top_level.txt
watson_form-4.4.2.dist-info/RECORD
