Metadata-Version: 2.1
Name: watson-form
Version: 4.4.2
Summary: Make working with HTML forms more tolerable.
Home-page: http://github.com/watsonpy/watson-form
Author: Simon Coulton
Author-email: simon@bespohk.com
License: Copyright (c) Bespohk and individual contributors.
Requires-Dist: watson-common (>=1.3.0)
Requires-Dist: watson-html (>=1.2.0)
Requires-Dist: watson-validators (>=1.0.2)
Requires-Dist: watson-filters (>=1.0.0)
Requires-Dist: watson-http (>=1.2.4)
Provides-Extra: test
Requires-Dist: pytest ; extra == 'test'
Requires-Dist: pytest-cov ; extra == 'test'
Requires-Dist: coverage ; extra == 'test'
Requires-Dist: coveralls ; extra == 'test'
Requires-Dist: watson-http (>=1.1.3) ; extra == 'test'
